aiographql.py
aiographql-0.2.1.dist-info/DESCRIPTION.rst
aiographql-0.2.1.dist-info/METADATA
aiographql-0.2.1.dist-info/RECORD
aiographql-0.2.1.dist-info/WHEEL
aiographql-0.2.1.dist-info/metadata.json
aiographql-0.2.1.dist-info/top_level.txt
