Metadata-Version: 2.0
Name: aiographql
Version: 0.2.1
Summary: asyncio + graphql = fast and simple api
Home-page: https://github.com/academicmerit/aiographql
Author: Denis Ryzhkov
Author-email: denisr@denisr.com
License: MIT
Keywords: asyncio graphql graphene uvloop
Platform: UNKNOWN
Classifier: Development Status :: 4 - Beta
Classifier: License :: OSI Approved :: MIT License
Classifier: Operating System :: POSIX :: Linux
Classifier: Operating System :: Unix
Classifier: Programming Language :: Python :: 3.5
Classifier: Programming Language :: Python :: 3 :: Only
Classifier: Topic :: Software Development :: Libraries :: Application Frameworks
Classifier: Topic :: Software Development :: Libraries :: Python Modules
Requires-Python: >=3.5
Requires-Dist: graphene (<3,>=2.0.1)
Requires-Dist: graphql-core (<3,>=2.0)
Requires-Dist: ujson (<2,>=1.35)
Requires-Dist: uvloop (<1,>=0.9.1)
